{"version":"1.4.0-alpha","line":{"mode":"TRAM","index":{"mode":"TRAM","$builtinLineIndex":{"index":"12"}},"color":"#b80b4b","lineThickness":"0.625","lineStyle":"STRIPED","dotsColorPolicy":"INHERIT","fullyAccessible":true,"frameTerminusNames":true,"mapSize":15,"topology":[{"id":"1","$lineSection":{"elements":[{"id":"b9007954-ec3e-4880-8b9e-2302d9988692","$branch":{"elementSpacing":"3","marginLeft":0,"marginRight":0,"invertedElements":false,"elements":[{"id":"9ce360b4-d276-495d-8a62-da5ee7d1d297","$stop":{"name":"Massy – Palaiseau","placeName":"","subtitle":"","accessible":"undefined","reverse":false,"interestPoint":false,"preventSubtitleOverlapping":true,"closed":false,"terminus":true,"connections":[{"id":"31b74e7b-faa0-48ef-b32e-24b36d8c5e11","$modeConnection":{"mode":"RER","elements":[{"id":"1f5afe1a-d8d6-4d35-bbff-02532abf404d","$modeConnectionElement":{"lineIndex":{"mode":"RER","$builtinLineIndex":{"index":"B"}},"walk":false,"ornament":{"id":"c9428d7f-7705-483d-b4c2-741c4a64cdec","position":"RIGHT","$airportOrnament":{"airport":"BOTH"}}}},{"id":"61968b91-d41e-4131-b188-47dcf363cf19","$modeConnectionElement":{"lineIndex":{"mode":"RER","$builtinLineIndex":{"index":"C"}},"walk":false,"ornament":null}}],"walk":false}},{"id":"6ad4bbb4-3852-4239-b783-77b0e0a70929","$modeConnection":{"mode":"TRAIN","elements":[{"id":"e7e75763-e772-45f1-baf6-e7aceb2ee0c6","$modeConnectionElement":{"lineIndex":{"mode":"TRAIN","$builtinLineIndex":{"index":"V"}},"walk":false,"ornament":null}}],"walk":false}},{"id":"e631c640-5203-446c-b046-0cf28a48e57b","$serviceConnection":{"elements":[{"id":"abb4c2c3-3048-44af-a0db-19f3657b51cb","$serviceConnectionElement":{"service":"MAIN_STATION","ornament":null}}],"walk":false}}]}},{"id":"95f95b99-d1e9-4661-98f1-e88f7863b892","$stop":{"name":"Massy – Europe","placeName":"","subtitle":"","accessible":"undefined","reverse":false,"interestPoint":false,"preventSubtitleOverlapping":true,"closed":false,"terminus":false,"connections":[]}},{"id":"43916e22-2e02-4ed7-b84a-8e14436533c6","$stop":{"name":"Champlan","placeName":"","subtitle":"","accessible":"undefined","reverse":false,"interestPoint":false,"preventSubtitleOverlapping":true,"closed":false,"terminus":false,"connections":[]}},{"id":"ee26e8a1-c3d0-4fae-b1b2-72bc66c2de7d","$stop":{"name":"Longjumeau","placeName":"","subtitle":"","accessible":"undefined","reverse":false,"interestPoint":false,"preventSubtitleOverlapping":true,"closed":false,"terminus":false,"connections":[]}},{"id":"d0972c6b-5fc6-4e06-95bf-62e339131426","$stop":{"name":"Chilly – Mazarin","placeName":"","subtitle":"","accessible":"undefined","reverse":false,"interestPoint":false,"preventSubtitleOverlapping":true,"closed":false,"terminus":false,"connections":[]}},{"id":"dc86612b-9693-465d-8ef7-6ff9b089c030","$stop":{"name":"Gravigny – Balizy","placeName":"","subtitle":"","accessible":"undefined","reverse":false,"interestPoint":false,"preventSubtitleOverlapping":true,"closed":false,"terminus":false,"connections":[]}},{"id":"2745ad6a-8270-462c-8a33-96704133f070","$stop":{"name":"Petit Vaux","placeName":"","subtitle":"","accessible":"undefined","reverse":false,"interestPoint":false,"preventSubtitleOverlapping":true,"closed":false,"terminus":false,"connections":[]}},{"id":"2723d320-99b4-493b-bd49-de8a21073b6a","$stop":{"name":"Épinay-sur-Orge","placeName":"","subtitle":"","accessible":"undefined","reverse":false,"interestPoint":false,"preventSubtitleOverlapping":true,"closed":false,"terminus":false,"connections":[{"id":"bedfc3d9-2cf0-4629-885d-6444cade31cf","$modeConnection":{"mode":"RER","elements":[{"id":"49e1fda1-30c0-4e2a-a06f-916bad7e0d59","$modeConnectionElement":{"lineIndex":{"mode":"RER","$builtinLineIndex":{"index":"C"}},"walk":false,"ornament":null}}],"walk":true}}]}},{"id":"baf36fc7-d438-4c7a-a366-632db30c9482","$stop":{"name":"Parc du Château","placeName":"","subtitle":"","accessible":"undefined","reverse":false,"interestPoint":false,"preventSubtitleOverlapping":true,"closed":false,"terminus":false,"connections":[]}},{"id":"0fec38ed-b1dc-488e-b312-7f47732ee98a","$stop":{"name":"Coteaux de l’Orge","placeName":"","subtitle":"","accessible":"undefined","reverse":false,"interestPoint":false,"preventSubtitleOverlapping":true,"closed":false,"terminus":false,"connections":[]}},{"id":"de6030f3-6c4a-45d0-a9ab-c4b3513f9175","$stop":{"name":"Amédée Gordini","placeName":"","subtitle":"","accessible":"undefined","reverse":false,"interestPoint":false,"preventSubtitleOverlapping":true,"closed":false,"terminus":false,"connections":[]}},{"id":"cadcda75-6975-4ecc-a405-5e43156c21f5","$stop":{"name":"Ferme Neuve","placeName":"","subtitle":"","accessible":"undefined","reverse":false,"interestPoint":false,"preventSubtitleOverlapping":true,"closed":false,"terminus":false,"connections":[]}},{"id":"090fb927-a1d4-432d-ae49-58052f77e81d","$stop":{"name":"Bois de Saint-Europe","placeName":"","subtitle":"","accessible":"undefined","reverse":false,"interestPoint":false,"preventSubtitleOverlapping":true,"closed":false,"terminus":false,"connections":[]}},{"id":"4e78072f-b740-4d4e-882d-a175c94e4eb3","$stop":{"name":"Traité de Rome","placeName":"","subtitle":"","accessible":"undefined","reverse":false,"interestPoint":false,"preventSubtitleOverlapping":true,"closed":false,"terminus":false,"connections":[]}},{"id":"8880c0a2-17a5-4194-823b-e658b72fe456","$stop":{"name":"Bois Briard","placeName":"","subtitle":"","accessible":"undefined","reverse":false,"interestPoint":false,"preventSubtitleOverlapping":true,"closed":false,"terminus":false,"connections":[]}},{"id":"7008fa82-8f05-4a31-8bf3-6eae1ff84f85","$stop":{"name":"Évry – Courcouronnes","placeName":"","subtitle":"","accessible":"undefined","reverse":false,"interestPoint":false,"preventSubtitleOverlapping":true,"closed":false,"terminus":true,"connections":[{"id":"35e48265-a214-435c-b778-24572819a3f2","$modeConnection":{"mode":"RER","elements":[{"id":"8a490670-4469-4639-86ad-e0b5c6d52a78","$modeConnectionElement":{"lineIndex":{"mode":"RER","$builtinLineIndex":{"index":"D"}},"walk":false,"ornament":null}}],"walk":true}}]}}]}}]}}]},"customIndices":[]}